datalab_sdk/__init__.py
datalab_sdk/cli.py
datalab_sdk/client.py
datalab_sdk/exceptions.py
datalab_sdk/mimetypes.py
datalab_sdk/models.py
datalab_sdk/settings.py
datalab_python_sdk-0.2.1.dist-info/METADATA
datalab_python_sdk-0.2.1.dist-info/WHEEL
datalab_python_sdk-0.2.1.dist-info/entry_points.txt
datalab_python_sdk-0.2.1.dist-info/licenses/LICENSE
datalab_python_sdk-0.2.1.dist-info/RECORD
