Metadata-Version: 2.4
Name: datalab-python-sdk
Version: 0.2.1
Summary: SDK for the Datalab document intelligence API
Author-email: Datalab Team <hi@datalab.to>
License-Expression: MIT
License-File: LICENSE
Keywords: api,datalab,document-intelligence,sdk
Requires-Python: >=3.10
Requires-Dist: aiohttp>=3.12.14
Requires-Dist: click>=8.2.1
Requires-Dist: pydantic-settings>=2.10.1
Requires-Dist: pydantic>=2.11.7
Requires-Dist: tenacity>=8.2.3
Requires-Dist: tqdm>=4.66.0
